ezpypi/__init__.py
ezpypi/core/__init__.py
ezpypi/core/main.py
ezpypi-0.2.0.dist-info/LICENSE
ezpypi-0.2.0.dist-info/METADATA
ezpypi-0.2.0.dist-info/WHEEL
ezpypi-0.2.0.dist-info/top_level.txt
ezpypi-0.2.0.dist-info/RECORD
