Metadata-Version: 2.1
Name: ezpypi
Version: 0.2.0
Summary: A Python publication tool for painlessly uploading your package to GitHub, Test PyPI, and PyPI.
Home-page: https://github.com/ZacksAmber/EzPyPI
Author: Zacks Shen
Author-email: zacks.shen@gmail.com
License: MIT
Project-URL: Bug Tracker, https://github.com/ZacksAmber/EzPyPI/issues
Project-URL: Changelog, https://github.com/ZacksAmber/EzPyPI/blob/main/CHANGELOG.md
Platform: UNKNOWN
Classifier: Development Status :: 2 - Pre-Alpha
Classifier: Environment :: Console
Classifier: Intended Audience :: Developers
Classifier: License :: OSI Approved :: MIT License
Classifier: Natural Language :: English
Classifier: Operating System :: OS Independent
Classifier: Programming Language :: Python
Classifier: Programming Language :: Python :: 3
Classifier: Programming Language :: Python :: 3.6
Classifier: Programming Language :: Python :: 3.7
Classifier: Programming Language :: Python :: 3.8
Classifier: Programming Language :: Python :: 3.9
Classifier: Topic :: Software Development :: Libraries :: Python Modules
Requires-Python: >=3.6
License-File: LICENSE
Requires-Dist: requests
Requires-Dist: setuptools
Requires-Dist: wheel
Requires-Dist: twine
Requires-Dist: build
